ml_assert/__init__.py
ml_assert/cli.py
ml_assert/core/base.py
ml_assert/core/dsl.py
ml_assert/data/checks.py
ml_assert/fairness/explainability.py
ml_assert/fairness/fairness.py
ml_assert/integrations/mlflow.py
ml_assert/integrations/prometheus.py
ml_assert/integrations/slack.py
ml_assert/model/cross_validation.py
ml_assert/model/performance.py
ml_assert/plugins/base.py
ml_assert/plugins/dvc_check.py
ml_assert/plugins/file_exists.py
ml_assert/schema.py
ml_assert/stats/__init__.py
ml_assert/stats/distribution.py
ml_assert/stats/drift.py
ml_assert-1.0.5.dist-info/LICENSE
ml_assert-1.0.5.dist-info/METADATA
ml_assert-1.0.5.dist-info/WHEEL
ml_assert-1.0.5.dist-info/entry_points.txt
ml_assert-1.0.5.dist-info/RECORD
