Metadata-Version: 2.3
Name: ml-assert
Version: 1.0.5
Summary: A comprehensive assertion-and-validation toolkit for ML workflows.
License: Apache License
Keywords: ml,machine-learning,testing,validation,assertion,mlops
Author: PyBrainn
Author-email: pybrainn@heyshinde.com
Maintainer: Shinde Aditya
Maintainer-email: aditya@heyshinde.com
Requires-Python: >=3.11
Classifier: Development Status :: 4 - Beta
Classifier: Intended Audience :: Developers
Classifier: Intended Audience :: Science/Research
Classifier: License :: OSI Approved :: Apache Software License
Classifier: Operating System :: OS Independent
Classifier: Programming Language :: Python :: 3
Classifier: Programming Language :: Python :: 3.10
Classifier: Programming Language :: Python :: 3.11
Classifier: Topic :: Scientific/Engineering :: Artificial Intelligence
Classifier: Topic :: Software Development :: Libraries :: Python Modules
Classifier: Topic :: Software Development :: Testing
Provides-Extra: notebooks
Requires-Dist: ipykernel (>=6.29.5,<7.0.0) ; extra == "notebooks"
Requires-Dist: jupytext (>=1.17.2,<2.0.0) ; extra == "notebooks"
Requires-Dist: mlflow (>=2.10.0,<3.0.0)
Requires-Dist: pandas (>=2.3.0,<3.0.0)
Requires-Dist: prometheus_client (>=0.21.0,<0.21.1)
Requires-Dist: pyyaml (>=6.0.2,<7.0.0)
Requires-Dist: scikit-learn (>=1.7.0,<2.0.0)
Requires-Dist: scipy (>=1.15.3,<2.0.0)
Requires-Dist: shap (>=0.47.2,<0.48.0)
Requires-Dist: typer[all] (>=0.16.0,<0.17.0)
Project-URL: Bug Tracker, https://github.com/pybrainn/ml-assert/issues
Project-URL: Homepage, https://github.io/PyBrainn/ml-assert
Project-URL: Repository, https://github.com/pybrainn/ml-assert
